{
	"60563": {
		"id": 60563,
		"barrage_ID": [
			1511,
			1512,
			1513
		],
		"name": "\u822a\u7a7a\u653b\u51fb\u5c55\u793a-\u4fe1\u6d53III",
		"base": 60561
	},
	"60502": {
		"name": "\u8d1e\u5fb7\u5f39\u5e55\u5c55\u793aII",
		"barrage_ID": [
			79543,
			79544,
			79545
		],
		"id": 60502,
		"bullet_ID": [
			79541,
			79541,
			79542
		],
		"base": 60501,
		"damage": 25
	},
	"60441": {
		"search_type": 1,
		"attack_attribute": 0,
		"shakescreen": 0,
		"angle": 30,
		"reload_max": 1750,
		"torpedo_ammo": 0,
		"queue": 1,
		"name": "\u822a\u7a7a\u653b\u51fb\u5c55\u793a-\u7d2b\u54b2\u8bd7\u97f3I",
		"fire_fx": "",
		"charge_param": "",
		"suppress": 1,
		"range": 90,
		"recover_time": 0.5,
		"fire_fx_loop_type": 1,
		"precast_param": [],
		"expose": 0,
		"attack_attribute_ratio": 100,
		"damage": 18,
		"action_index": "attack",
		"type": 99,
		"search_condition": [
			1
		],
		"oxy_type": [
			1
		],
		"id": 60441,
		"spawn_bound": "plane",
		"barrage_ID": [
			1511,
			1510
		],
		"corrected": 100,
		"auto_aftercast": 0,
		"bullet_ID": [
			37100,
			38000
		],
		"min_range": 0,
		"initial_over_heat": 0,
		"aim_type": 1,
		"fire_sfx": "battle/air-atk",
		"effect_move": 1,
		"axis_angle": 0
	},
	"60443": {
		"id": 60443,
		"barrage_ID": [
			1512,
			1512
		],
		"name": "\u822a\u7a7a\u653b\u51fb\u5c55\u793a-\u7d2b\u54b2\u8bd7\u97f3III",
		"base": 60441
	},
	"60382": {
		"id": 60382,
		"barrage_ID": [
			1511,
			1511
		],
		"name": "\u822a\u7a7a\u653b\u51fb\u5c55\u793a-\u8ffd\u8d76\u8005II",
		"base": 60381
	},
	"60512": {
		"id": 60512,
		"barrage_ID": [
			1511,
			1511
		],
		"name": "\u822a\u7a7a\u653b\u51fb\u5c55\u793a-\u8d1d\u4e9a\u6069II",
		"base": 60511
	},
	"60451": {
		"search_type": 1,
		"attack_attribute": 0,
		"shakescreen": 0,
		"angle": 30,
		"reload_max": 1750,
		"torpedo_ammo": 0,
		"queue": 1,
		"name": "\u822a\u7a7a\u653b\u51fb\u5c55\u793a-\u5927\u795e\u6faaI",
		"fire_fx": "",
		"charge_param": "",
		"suppress": 1,
		"range": 90,
		"recover_time": 0.5,
		"fire_fx_loop_type": 1,
		"precast_param": [],
		"expose": 0,
		"attack_attribute_ratio": 100,
		"damage": 18,
		"action_index": "attack",
		"type": 99,
		"search_condition": [
			1
		],
		"oxy_type": [
			1
		],
		"id": 60451,
		"spawn_bound": "plane",
		"barrage_ID": [
			1510,
			1511,
			1510
		],
		"corrected": 100,
		"auto_aftercast": 0,
		"bullet_ID": [
			37100,
			39000,
			38000
		],
		"min_range": 0,
		"initial_over_heat": 0,
		"aim_type": 1,
		"fire_sfx": "battle/air-atk",
		"effect_move": 1,
		"axis_angle": 0
	},
	"60453": {
		"id": 60453,
		"barrage_ID": [
			1511,
			1512,
			1512
		],
		"name": "\u822a\u7a7a\u653b\u51fb\u5c55\u793a-\u5927\u795e\u6faaIII",
		"base": 60451
	},
	"60392": {
		"id": 60392,
		"barrage_ID": [
			1511,
			1511
		],
		"name": "\u822a\u7a7a\u653b\u51fb\u5c55\u793a-\u72ec\u7acbII",
		"base": 60391
	},
	"60522": {
		"id": 60522,
		"barrage_ID": [
			1511,
			1511
		],
		"name": "\u822a\u7a7a\u653b\u51fb\u5c55\u793a-\u82f1\u4ed9\u5ea7II",
		"base": 60521
	},
	"60461": {
		"search_type": 1,
		"attack_attribute": 0,
		"shakescreen": 0,
		"angle": 30,
		"reload_max": 1750,
		"torpedo_ammo": 0,
		"queue": 1,
		"name": "\u822a\u7a7a\u653b\u51fb\u5c55\u793a-\u767d\u4e0a\u5439\u96eaIII",
		"fire_fx": "",
		"charge_param": "",
		"suppress": 1,
		"range": 90,
		"recover_time": 0.5,
		"fire_fx_loop_type": 1,
		"precast_param": [],
		"expose": 0,
		"attack_attribute_ratio": 100,
		"damage": 18,
		"action_index": "attack",
		"type": 99,
		"search_condition": [
			1
		],
		"oxy_type": [
			1
		],
		"id": 60461,
		"spawn_bound": "plane",
		"barrage_ID": [
			1511
		],
		"corrected": 100,
		"auto_aftercast": 0,
		"bullet_ID": [
			68951
		],
		"min_range": 0,
		"initial_over_heat": 0,
		"aim_type": 1,
		"fire_sfx": "battle/air-atk",
		"effect_move": 1,
		"axis_angle": 0
	},
	"60582": {
		"name": "\u6076\u6bd2\u5f39\u5e55\u5c55\u793aII",
		"id": 60582,
		"barrage_ID": [
			79623,
			79624,
			79625
		],
		"base": 60581,
		"damage": 20
	},
	"60402": {
		"id": 60402,
		"barrage_ID": [
			1510,
			1511,
			1511
		],
		"name": "\u822a\u7a7a\u653b\u51fb\u5c55\u793a-\u7231\u9171II",
		"base": 60401
	},
	"60581": {
		"search_type": 1,
		"attack_attribute": 1,
		"shakescreen": 0,
		"angle": 360,
		"reload_max": 400,
		"torpedo_ammo": 0,
		"queue": 1,
		"name": "\u6076\u6bd2\u5f39\u5e55\u5c55\u793aI",
		"fire_fx": "CLFire",
		"charge_param": "",
		"suppress": 0,
		"range": 50,
		"recover_time": 0.5,
		"fire_fx_loop_type": 1,
		"precast_param": [],
		"expose": 0,
		"attack_attribute_ratio": 100,
		"damage": 12,
		"action_index": "attack",
		"type": 2,
		"search_condition": [
			1
		],
		"oxy_type": [
			1
		],
		"id": 60581,
		"spawn_bound": "cannon",
		"barrage_ID": [
			79621,
			79622,
			79625
		],
		"corrected": 125,
		"auto_aftercast": 0,
		"bullet_ID": [
			79621,
			79621,
			79622
		],
		"min_range": 0,
		"initial_over_heat": 0,
		"aim_type": 0,
		"fire_sfx": "battle/cannon-155mm",
		"effect_move": 0,
		"axis_angle": 0
	},
	"60532": {
		"id": 60532,
		"barrage_ID": [
			1511,
			1511
		],
		"name": "\u822a\u7a7a\u653b\u51fb\u5c55\u793a-\u9e70II",
		"base": 60531
	},
	"60471": {
		"search_type": 1,
		"attack_attribute": 0,
		"shakescreen": 0,
		"angle": 30,
		"reload_max": 1750,
		"torpedo_ammo": 0,
		"queue": 1,
		"name": "\u822a\u7a7a\u653b\u51fb\u5c55\u793a-\u9f99\u51e4I",
		"fire_fx": "",
		"charge_param": "",
		"suppress": 1,
		"range": 90,
		"recover_time": 0.5,
		"fire_fx_loop_type": 1,
		"precast_param": [],
		"expose": 0,
		"attack_attribute_ratio": 100,
		"damage": 18,
		"action_index": "attack",
		"type": 99,
		"search_condition": [
			1
		],
		"oxy_type": [
			1
		],
		"id": 60471,
		"spawn_bound": "plane",
		"barrage_ID": [
			1511,
			1510
		],
		"corrected": 100,
		"auto_aftercast": 0,
		"bullet_ID": [
			37100,
			38000
		],
		"min_range": 0,
		"initial_over_heat": 0,
		"aim_type": 1,
		"fire_sfx": "battle/air-atk",
		"effect_move": 1,
		"axis_angle": 0
	},
	"60473": {
		"id": 60473,
		"barrage_ID": [
			1512,
			1512
		],
		"name": "\u822a\u7a7a\u653b\u51fb\u5c55\u793a-\u9f99\u51e4III",
		"base": 60471
	},
	"60412": {
		"id": 60412,
		"barrage_ID": [
			1511,
			1511,
			1511
		],
		"name": "\u822a\u7a7a\u653b\u51fb\u5c55\u793a-\u5c0f\u9f50\u67cf\u6797II",
		"base": 60411
	},
	"60572": {
		"name": "\u51c9\u6708\u5f39\u5e55\u5c55\u793aII",
		"barrage_ID": [
			79601,
			79602,
			79603,
			79604
		],
		"id": 60572,
		"bullet_ID": [
			79601,
			79601,
			79601,
			79602
		],
		"base": 60571,
		"damage": 20
	},
	"60542": {
		"id": 60542,
		"barrage_ID": [
			1511,
			1511
		],
		"name": "\u822a\u7a7a\u653b\u51fb\u5c55\u793a-\u5343\u5c81II",
		"base": 60541
	},
	"60481": {
		"search_type": 1,
		"attack_attribute": 1,
		"shakescreen": 0,
		"angle": 360,
		"reload_max": 400,
		"torpedo_ammo": 0,
		"queue": 1,
		"name": "\u80fd\u4ee3\u5f39\u5e55\u5c55\u793aI",
		"fire_fx": "CLFire",
		"charge_param": "",
		"suppress": 0,
		"range": 50,
		"recover_time": 0.5,
		"fire_fx_loop_type": 1,
		"precast_param": [],
		"expose": 0,
		"attack_attribute_ratio": 100,
		"damage": 12,
		"action_index": "attack",
		"type": 2,
		"search_condition": [
			1
		],
		"oxy_type": [
			1
		],
		"id": 60481,
		"spawn_bound": "cannon",
		"barrage_ID": [
			79481,
			79482
		],
		"corrected": 125,
		"auto_aftercast": 0,
		"bullet_ID": [
			79481,
			79481
		],
		"min_range": 0,
		"initial_over_heat": 0,
		"aim_type": 0,
		"fire_sfx": "battle/cannon-155mm",
		"effect_move": 0,
		"axis_angle": 0
	},
	"60571": {
		"search_type": 1,
		"attack_attribute": 1,
		"shakescreen": 0,
		"angle": 360,
		"reload_max": 400,
		"torpedo_ammo": 0,
		"queue": 1,
		"name": "\u51c9\u6708\u5f39\u5e55\u5c55\u793aI",
		"fire_fx": "CLFire",
		"charge_param": "",
		"suppress": 0,
		"range": 50,
		"recover_time": 0.5,
		"fire_fx_loop_type": 1,
		"precast_param": [],
		"expose": 0,
		"attack_attribute_ratio": 100,
		"damage": 12,
		"action_index": "attack",
		"type": 2,
		"search_condition": [
			1
		],
		"oxy_type": [
			1
		],
		"id": 60571,
		"spawn_bound": "cannon",
		"barrage_ID": [
			79601,
			79602,
			79603
		],
		"corrected": 125,
		"auto_aftercast": 0,
		"bullet_ID": [
			79601,
			79601,
			79601
		],
		"min_range": 0,
		"initial_over_heat": 0,
		"aim_type": 0,
		"fire_sfx": "battle/cannon-155mm",
		"effect_move": 0,
		"axis_angle": 0
	},
	"60422": {
		"id": 60422,
		"barrage_ID": [
			1511,
			1511,
			1511
		],
		"name": "\u822a\u7a7a\u653b\u51fb\u5c55\u793a-\u53ef\u754fII",
		"base": 60421
	},
	"60562": {
		"id": 60562,
		"barrage_ID": [
			1510,
			1511,
			1512
		],
		"name": "\u822a\u7a7a\u653b\u51fb\u5c55\u793a-\u4fe1\u6d53II",
		"base": 60561
	},
	"60363": {
		"id": 60363,
		"barrage_ID": [
			1512,
			1512
		],
		"name": "\u822a\u7a7a\u653b\u51fb\u5c55\u793a-\u8428\u83c8\u5a1cIII",
		"base": 60361
	},
	"60491": {
		"search_type": 1,
		"attack_attribute": 0,
		"shakescreen": 0,
		"angle": 30,
		"reload_max": 1750,
		"torpedo_ammo": 0,
		"queue": 1,
		"name": "\u822a\u7a7a\u653b\u51fb\u5c55\u793a-\u5361\u8428\u5e03\u5170\u5361I",
		"fire_fx": "",
		"charge_param": "",
		"suppress": 1,
		"range": 90,
		"recover_time": 0.5,
		"fire_fx_loop_type": 1,
		"precast_param": [],
		"expose": 0,
		"attack_attribute_ratio": 100,
		"damage": 18,
		"action_index": "attack",
		"type": 99,
		"search_condition": [
			1
		],
		"oxy_type": [
			1
		],
		"id": 60491,
		"spawn_bound": "plane",
		"barrage_ID": [
			1511,
			1510
		],
		"corrected": 100,
		"auto_aftercast": 0,
		"bullet_ID": [
			17000,
			19000
		],
		"min_range": 0,
		"initial_over_heat": 0,
		"aim_type": 1,
		"fire_sfx": "battle/air-atk",
		"effect_move": 1,
		"axis_angle": 0
	},
	"60493": {
		"id": 60493,
		"barrage_ID": [
			1512,
			1512
		],
		"name": "\u822a\u7a7a\u653b\u51fb\u5c55\u793a-\u5361\u8428\u5e03\u5170\u5361III",
		"base": 60491
	},
	"60432": {
		"id": 60432,
		"barrage_ID": [
			1510,
			1511,
			1511
		],
		"name": "\u822a\u7a7a\u653b\u51fb\u5c55\u793a-\u65f6\u4e43\u7a7aII",
		"base": 60431
	},
	"60371": {
		"search_type": 1,
		"attack_attribute": 0,
		"shakescreen": 0,
		"angle": 30,
		"reload_max": 1750,
		"torpedo_ammo": 0,
		"queue": 1,
		"name": "\u822a\u7a7a\u653b\u51fb\u5c55\u793a-\u9f99\u9aa7I",
		"fire_fx": "",
		"charge_param": "",
		"suppress": 1,
		"range": 90,
		"recover_time": 0.5,
		"fire_fx_loop_type": 1,
		"precast_param": [],
		"expose": 0,
		"attack_attribute_ratio": 100,
		"damage": 18,
		"action_index": "attack",
		"type": 99,
		"search_condition": [
			1
		],
		"oxy_type": [
			1
		],
		"id": 60371,
		"spawn_bound": "plane",
		"barrage_ID": [
			1511,
			1510
		],
		"corrected": 100,
		"auto_aftercast": 0,
		"bullet_ID": [
			37000,
			38000
		],
		"min_range": 0,
		"initial_over_heat": 0,
		"aim_type": 1,
		"fire_sfx": "battle/air-atk",
		"effect_move": 1,
		"axis_angle": 0
	},
	"60373": {
		"id": 60373,
		"barrage_ID": [
			1512,
			1512
		],
		"name": "\u822a\u7a7a\u653b\u51fb\u5c55\u793a-\u9f99\u9aa7III",
		"base": 60371
	},
	"60501": {
		"search_type": 1,
		"attack_attribute": 1,
		"shakescreen": 0,
		"angle": 360,
		"reload_max": 400,
		"torpedo_ammo": 0,
		"queue": 1,
		"name": "\u8d1e\u5fb7\u5f39\u5e55\u5c55\u793aI",
		"fire_fx": "CLFire",
		"charge_param": "",
		"suppress": 0,
		"range": 50,
		"recover_time": 0.5,
		"fire_fx_loop_type": 1,
		"precast_param": [],
		"expose": 0,
		"attack_attribute_ratio": 100,
		"damage": 12,
		"action_index": "attack",
		"type": 2,
		"search_condition": [
			1
		],
		"oxy_type": [
			1
		],
		"id": 60501,
		"spawn_bound": "cannon",
		"barrage_ID": [
			79541,
			79542
		],
		"corrected": 125,
		"auto_aftercast": 0,
		"bullet_ID": [
			79541,
			79541
		],
		"min_range": 0,
		"initial_over_heat": 0,
		"aim_type": 0,
		"fire_sfx": "battle/cannon-155mm",
		"effect_move": 0,
		"axis_angle": 0
	},
	"60561": {
		"search_type": 1,
		"attack_attribute": 0,
		"shakescreen": 0,
		"angle": 30,
		"reload_max": 1750,
		"torpedo_ammo": 0,
		"queue": 1,
		"name": "\u822a\u7a7a\u653b\u51fb\u5c55\u793a-\u4fe1\u6d53I",
		"fire_fx": "",
		"charge_param": "",
		"suppress": 1,
		"range": 90,
		"recover_time": 0.5,
		"fire_fx_loop_type": 1,
		"precast_param": [],
		"expose": 0,
		"attack_attribute_ratio": 100,
		"damage": 18,
		"action_index": "attack",
		"type": 99,
		"search_condition": [
			1
		],
		"oxy_type": [
			1
		],
		"id": 60561,
		"spawn_bound": "plane",
		"barrage_ID": [
			1510,
			1511,
			1510
		],
		"corrected": 100,
		"auto_aftercast": 0,
		"bullet_ID": [
			37300,
			39000,
			38200
		],
		"min_range": 0,
		"initial_over_heat": 0,
		"aim_type": 1,
		"fire_sfx": "battle/air-atk",
		"effect_move": 1,
		"axis_angle": 0
	},
	"60442": {
		"id": 60442,
		"barrage_ID": [
			1511,
			1511
		],
		"name": "\u822a\u7a7a\u653b\u51fb\u5c55\u793a-\u7d2b\u54b2\u8bd7\u97f3II",
		"base": 60441
	},
	"60381": {
		"search_type": 1,
		"attack_attribute": 0,
		"shakescreen": 0,
		"angle": 30,
		"reload_max": 1750,
		"torpedo_ammo": 0,
		"queue": 1,
		"name": "\u822a\u7a7a\u653b\u51fb\u5c55\u793a-\u8ffd\u8d76\u8005I",
		"fire_fx": "",
		"charge_param": "",
		"suppress": 1,
		"range": 90,
		"recover_time": 0.5,
		"fire_fx_loop_type": 1,
		"precast_param": [],
		"expose": 0,
		"attack_attribute_ratio": 100,
		"damage": 18,
		"action_index": "attack",
		"type": 99,
		"search_condition": [
			1
		],
		"oxy_type": [
			1
		],
		"id": 60381,
		"spawn_bound": "plane",
		"barrage_ID": [
			1511,
			1510
		],
		"corrected": 100,
		"auto_aftercast": 0,
		"bullet_ID": [
			17100,
			28000
		],
		"min_range": 0,
		"initial_over_heat": 0,
		"aim_type": 1,
		"fire_sfx": "battle/air-atk",
		"effect_move": 1,
		"axis_angle": 0
	},
	"60383": {
		"id": 60383,
		"barrage_ID": [
			1512,
			1512
		],
		"name": "\u822a\u7a7a\u653b\u51fb\u5c55\u793a-\u8ffd\u8d76\u8005III",
		"base": 60381
	},
	"60511": {
		"search_type": 1,
		"attack_attribute": 0,
		"shakescreen": 0,
		"angle": 30,
		"reload_max": 1750,
		"torpedo_ammo": 0,
		"queue": 1,
		"name": "\u822a\u7a7a\u653b\u51fb\u5c55\u793a-\u8d1d\u4e9a\u6069I",
		"fire_fx": "",
		"charge_param": "",
		"suppress": 1,
		"range": 90,
		"recover_time": 0.5,
		"fire_fx_loop_type": 1,
		"precast_param": [],
		"expose": 0,
		"attack_attribute_ratio": 100,
		"damage": 18,
		"action_index": "attack",
		"type": 99,
		"search_condition": [
			1
		],
		"oxy_type": [
			1
		],
		"id": 60511,
		"spawn_bound": "plane",
		"barrage_ID": [
			1511,
			1510
		],
		"corrected": 100,
		"auto_aftercast": 0,
		"bullet_ID": [
			90820,
			90840
		],
		"min_range": 0,
		"initial_over_heat": 0,
		"aim_type": 1,
		"fire_sfx": "battle/air-atk",
		"effect_move": 1,
		"axis_angle": 0
	},
	"60513": {
		"id": 60513,
		"barrage_ID": [
			1512,
			1512
		],
		"name": "\u822a\u7a7a\u653b\u51fb\u5c55\u793a-\u8d1d\u4e9a\u6069III",
		"base": 60511
	},
	"60452": {
		"id": 60452,
		"barrage_ID": [
			1510,
			1511,
			1511
		],
		"name": "\u822a\u7a7a\u653b\u51fb\u5c55\u793a-\u5927\u795e\u6faaII",
		"base": 60451
	},
	"60391": {
		"search_type": 1,
		"attack_attribute": 0,
		"shakescreen": 0,
		"angle": 30,
		"reload_max": 1750,
		"torpedo_ammo": 0,
		"queue": 1,
		"name": "\u822a\u7a7a\u653b\u51fb\u5c55\u793a-\u72ec\u7acbI",
		"fire_fx": "",
		"charge_param": "",
		"suppress": 1,
		"range": 90,
		"recover_time": 0.5,
		"fire_fx_loop_type": 1,
		"precast_param": [],
		"expose": 0,
		"attack_attribute_ratio": 100,
		"damage": 18,
		"action_index": "attack",
		"type": 99,
		"search_condition": [
			1
		],
		"oxy_type": [
			1
		],
		"id": 60391,
		"spawn_bound": "plane",
		"barrage_ID": [
			1511,
			1510
		],
		"corrected": 100,
		"auto_aftercast": 0,
		"bullet_ID": [
			17300,
			18100
		],
		"min_range": 0,
		"initial_over_heat": 0,
		"aim_type": 1,
		"fire_sfx": "battle/air-atk",
		"effect_move": 1,
		"axis_angle": 0
	},
	"60393": {
		"id": 60393,
		"barrage_ID": [
			1512,
			1512
		],
		"name": "\u822a\u7a7a\u653b\u51fb\u5c55\u793a-\u72ec\u7acbIII",
		"base": 60391
	},
	"60521": {
		"search_type": 1,
		"attack_attribute": 0,
		"shakescreen": 0,
		"angle": 30,
		"reload_max": 1750,
		"torpedo_ammo": 0,
		"queue": 1,
		"name": "\u822a\u7a7a\u653b\u51fb\u5c55\u793a-\u82f1\u4ed9\u5ea7I",
		"fire_fx": "",
		"charge_param": "",
		"suppress": 1,
		"range": 90,
		"recover_time": 0.5,
		"fire_fx_loop_type": 1,
		"precast_param": [],
		"expose": 0,
		"attack_attribute_ratio": 100,
		"damage": 18,
		"action_index": "attack",
		"type": 99,
		"search_condition": [
			1
		],
		"oxy_type": [
			1
		],
		"id": 60521,
		"spawn_bound": "plane",
		"barrage_ID": [
			1511,
			1510
		],
		"corrected": 100,
		"auto_aftercast": 0,
		"bullet_ID": [
			27000,
			28000
		],
		"min_range": 0,
		"initial_over_heat": 0,
		"aim_type": 1,
		"fire_sfx": "battle/air-atk",
		"effect_move": 1,
		"axis_angle": 0
	},
	"60523": {
		"id": 60523,
		"barrage_ID": [
			1512,
			1512
		],
		"name": "\u822a\u7a7a\u653b\u51fb\u5c55\u793a-\u82f1\u4ed9\u5ea7III",
		"base": 60521
	},
	"60552": {
		"id": 60552,
		"barrage_ID": [
			1511,
			1511
		],
		"name": "\u822a\u7a7a\u653b\u51fb\u5c55\u793a-\u5343\u4ee3\u7530II",
		"base": 60551
	},
	"60401": {
		"search_type": 1,
		"attack_attribute": 0,
		"shakescreen": 0,
		"angle": 30,
		"reload_max": 1750,
		"torpedo_ammo": 0,
		"queue": 1,
		"name": "\u822a\u7a7a\u653b\u51fb\u5c55\u793a-\u7231\u9171I",
		"fire_fx": "",
		"charge_param": "",
		"suppress": 1,
		"range": 90,
		"recover_time": 0.5,
		"fire_fx_loop_type": 1,
		"precast_param": [],
		"expose": 0,
		"attack_attribute_ratio": 100,
		"damage": 18,
		"action_index": "attack",
		"type": 99,
		"search_condition": [
			1
		],
		"oxy_type": [
			1
		],
		"id": 60401,
		"spawn_bound": "plane",
		"barrage_ID": [
			1510,
			1511,
			1510
		],
		"corrected": 100,
		"auto_aftercast": 0,
		"bullet_ID": [
			37100,
			39000,
			38000
		],
		"min_range": 0,
		"initial_over_heat": 0,
		"aim_type": 1,
		"fire_sfx": "battle/air-atk",
		"effect_move": 1,
		"axis_angle": 0
	},
	"60403": {
		"id": 60403,
		"barrage_ID": [
			1511,
			1512,
			1512
		],
		"name": "\u822a\u7a7a\u653b\u51fb\u5c55\u793a-\u7231\u9171III",
		"base": 60401
	},
	"60531": {
		"search_type": 1,
		"attack_attribute": 0,
		"shakescreen": 0,
		"angle": 30,
		"reload_max": 1750,
		"torpedo_ammo": 0,
		"queue": 1,
		"name": "\u822a\u7a7a\u653b\u51fb\u5c55\u793a-\u9e70I",
		"fire_fx": "",
		"charge_param": "",
		"suppress": 1,
		"range": 90,
		"recover_time": 0.5,
		"fire_fx_loop_type": 1,
		"precast_param": [],
		"expose": 0,
		"attack_attribute_ratio": 100,
		"damage": 18,
		"action_index": "attack",
		"type": 99,
		"search_condition": [
			1
		],
		"oxy_type": [
			1
		],
		"id": 60531,
		"spawn_bound": "plane",
		"barrage_ID": [
			1511,
			1510
		],
		"corrected": 100,
		"auto_aftercast": 0,
		"bullet_ID": [
			27000,
			28000
		],
		"min_range": 0,
		"initial_over_heat": 0,
		"aim_type": 1,
		"fire_sfx": "battle/air-atk",
		"effect_move": 1,
		"axis_angle": 0
	},
	"60533": {
		"id": 60533,
		"barrage_ID": [
			1512,
			1512
		],
		"name": "\u822a\u7a7a\u653b\u51fb\u5c55\u793a-\u9e70III",
		"base": 60531
	},
	"60472": {
		"id": 60472,
		"barrage_ID": [
			1511,
			1511
		],
		"name": "\u822a\u7a7a\u653b\u51fb\u5c55\u793a-\u9f99\u51e4II",
		"base": 60471
	},
	"60411": {
		"search_type": 1,
		"attack_attribute": 0,
		"shakescreen": 0,
		"angle": 30,
		"reload_max": 1750,
		"torpedo_ammo": 0,
		"queue": 1,
		"name": "\u822a\u7a7a\u653b\u51fb\u5c55\u793a-\u5c0f\u9f50\u67cf\u6797I",
		"fire_fx": "",
		"charge_param": "",
		"suppress": 1,
		"range": 90,
		"recover_time": 0.5,
		"fire_fx_loop_type": 1,
		"precast_param": [],
		"expose": 0,
		"attack_attribute_ratio": 100,
		"damage": 18,
		"action_index": "attack",
		"type": 99,
		"search_condition": [
			1
		],
		"oxy_type": [
			1
		],
		"id": 60411,
		"spawn_bound": "plane",
		"barrage_ID": [
			1511,
			1511,
			1510
		],
		"corrected": 100,
		"auto_aftercast": 0,
		"bullet_ID": [
			47000,
			49000,
			49000
		],
		"min_range": 0,
		"initial_over_heat": 0,
		"aim_type": 1,
		"fire_sfx": "battle/air-atk",
		"effect_move": 1,
		"axis_angle": 0
	},
	"60413": {
		"id": 60413,
		"barrage_ID": [
			1512,
			1512,
			1511
		],
		"name": "\u822a\u7a7a\u653b\u51fb\u5c55\u793a-\u5c0f\u9f50\u67cf\u6797III",
		"base": 60411
	},
	"60541": {
		"search_type": 1,
		"attack_attribute": 0,
		"shakescreen": 0,
		"angle": 30,
		"reload_max": 1750,
		"torpedo_ammo": 0,
		"queue": 1,
		"name": "\u822a\u7a7a\u653b\u51fb\u5c55\u793a-\u5343\u5c81I",
		"fire_fx": "",
		"charge_param": "",
		"suppress": 1,
		"range": 90,
		"recover_time": 0.5,
		"fire_fx_loop_type": 1,
		"precast_param": [],
		"expose": 0,
		"attack_attribute_ratio": 100,
		"damage": 18,
		"action_index": "attack",
		"type": 99,
		"search_condition": [
			1
		],
		"oxy_type": [
			1
		],
		"id": 60541,
		"spawn_bound": "plane",
		"barrage_ID": [
			1511,
			1510
		],
		"corrected": 100,
		"auto_aftercast": 0,
		"bullet_ID": [
			37100,
			38000
		],
		"min_range": 0,
		"initial_over_heat": 0,
		"aim_type": 1,
		"fire_sfx": "battle/air-atk",
		"effect_move": 1,
		"axis_angle": 0
	},
	"60543": {
		"id": 60543,
		"barrage_ID": [
			1512,
			1512
		],
		"name": "\u822a\u7a7a\u653b\u51fb\u5c55\u793a-\u5343\u5c81III",
		"base": 60541
	},
	"60482": {
		"name": "\u80fd\u4ee3\u5f39\u5e55\u5c55\u793aII",
		"barrage_ID": [
			79483,
			79484,
			79485
		],
		"id": 60482,
		"bullet_ID": [
			79481,
			79481,
			79482
		],
		"base": 60481,
		"damage": 25
	},
	"60421": {
		"search_type": 1,
		"attack_attribute": 0,
		"shakescreen": 0,
		"angle": 30,
		"reload_max": 1750,
		"torpedo_ammo": 0,
		"queue": 1,
		"name": "\u822a\u7a7a\u653b\u51fb\u5c55\u793a-\u53ef\u754fI",
		"fire_fx": "",
		"charge_param": "",
		"suppress": 1,
		"range": 90,
		"recover_time": 0.5,
		"fire_fx_loop_type": 1,
		"precast_param": [],
		"expose": 0,
		"attack_attribute_ratio": 100,
		"damage": 18,
		"action_index": "attack",
		"type": 99,
		"search_condition": [
			1
		],
		"oxy_type": [
			1
		],
		"id": 60421,
		"spawn_bound": "plane",
		"barrage_ID": [
			1510,
			1511,
			1511
		],
		"corrected": 100,
		"auto_aftercast": 0,
		"bullet_ID": [
			27000,
			28300,
			28300
		],
		"min_range": 0,
		"initial_over_heat": 0,
		"aim_type": 1,
		"fire_sfx": "battle/air-atk",
		"effect_move": 1,
		"axis_angle": 0
	},
	"60423": {
		"id": 60423,
		"barrage_ID": [
			1511,
			1512,
			1512
		],
		"name": "\u822a\u7a7a\u653b\u51fb\u5c55\u793a-\u53ef\u754fIII",
		"base": 60421
	},
	"60362": {
		"id": 60362,
		"barrage_ID": [
			1511,
			1511
		],
		"name": "\u822a\u7a7a\u653b\u51fb\u5c55\u793a-\u8428\u83c8\u5a1cII",
		"base": 60361
	},
	"60553": {
		"id": 60553,
		"barrage_ID": [
			1512,
			1512
		],
		"name": "\u822a\u7a7a\u653b\u51fb\u5c55\u793a-\u5343\u4ee3\u7530III",
		"base": 60551
	},
	"60492": {
		"id": 60492,
		"barrage_ID": [
			1511,
			1511
		],
		"name": "\u822a\u7a7a\u653b\u51fb\u5c55\u793a-\u5361\u8428\u5e03\u5170\u5361II",
		"base": 60491
	},
	"60431": {
		"search_type": 1,
		"attack_attribute": 0,
		"shakescreen": 0,
		"angle": 30,
		"reload_max": 1750,
		"torpedo_ammo": 0,
		"queue": 1,
		"name": "\u822a\u7a7a\u653b\u51fb\u5c55\u793a-\u65f6\u4e43\u7a7aI",
		"fire_fx": "",
		"charge_param": "",
		"suppress": 1,
		"range": 90,
		"recover_time": 0.5,
		"fire_fx_loop_type": 1,
		"precast_param": [],
		"expose": 0,
		"attack_attribute_ratio": 100,
		"damage": 18,
		"action_index": "attack",
		"type": 99,
		"search_condition": [
			1
		],
		"oxy_type": [
			1
		],
		"id": 60431,
		"spawn_bound": "plane",
		"barrage_ID": [
			1510,
			1511,
			1510
		],
		"corrected": 100,
		"auto_aftercast": 0,
		"bullet_ID": [
			37100,
			39000,
			38000
		],
		"min_range": 0,
		"initial_over_heat": 0,
		"aim_type": 1,
		"fire_sfx": "battle/air-atk",
		"effect_move": 1,
		"axis_angle": 0
	},
	"60433": {
		"id": 60433,
		"barrage_ID": [
			1511,
			1512,
			1512
		],
		"name": "\u822a\u7a7a\u653b\u51fb\u5c55\u793a-\u65f6\u4e43\u7a7aIII",
		"base": 60431
	},
	"60372": {
		"id": 60372,
		"barrage_ID": [
			1511,
			1511
		],
		"name": "\u822a\u7a7a\u653b\u51fb\u5c55\u793a-\u9f99\u9aa7II",
		"base": 60371
	},
	"60551": {
		"search_type": 1,
		"attack_attribute": 0,
		"shakescreen": 0,
		"angle": 30,
		"reload_max": 1750,
		"torpedo_ammo": 0,
		"queue": 1,
		"name": "\u822a\u7a7a\u653b\u51fb\u5c55\u793a-\u5343\u4ee3\u7530I",
		"fire_fx": "",
		"charge_param": "",
		"suppress": 1,
		"range": 90,
		"recover_time": 0.5,
		"fire_fx_loop_type": 1,
		"precast_param": [],
		"expose": 0,
		"attack_attribute_ratio": 100,
		"damage": 18,
		"action_index": "attack",
		"type": 99,
		"search_condition": [
			1
		],
		"oxy_type": [
			1
		],
		"id": 60551,
		"spawn_bound": "plane",
		"barrage_ID": [
			1511,
			1510
		],
		"corrected": 100,
		"auto_aftercast": 0,
		"bullet_ID": [
			37100,
			38000
		],
		"min_range": 0,
		"initial_over_heat": 0,
		"aim_type": 1,
		"fire_sfx": "battle/air-atk",
		"effect_move": 1,
		"axis_angle": 0
	}
}