{
	"fadeOut": 1.5,
	"fadein": 1.5,
	"scripts": [
		{
			"actor": 205100,
			"side": 2,
			"dir": 1,
			"nameColor": "#a9f548",
			"expression": 1,
			"painting": {
				"alpha": 0.3,
				"time": 1
			},
			"flashin": {
				"alpha": [
					1,
					0
				],
				"black": true,
				"delay": 1,
				"dur": 1
			},
			"say": "\u5601\uff0c\u867d\u7136\u5df2\u7ecf\u6709\u4e86\u5fc3\u7406\u51c6\u5907\uff0c\u4f46\u8fd9\u65b0\u578b\u585e\u58ec\u2026\u5b9e\u9645\u4f53\u9a8c\u4e0b\u6765\u6bd4\u8bb0\u5f55\u4e2d\u8fd8\u8981\u68d8\u624b\u3002\u518d\u8fd9\u4e48\u88ab\u62d6\u4e0b\u53bb\u5c31\u9ebb\u70e6\u4e86\u2026\uff01",
			"typewriter": {
				"speed": 0.05,
				"speedUp": 0.01
			},
			"bgm": "bgm-cccp2",
			"bgmDelay": 1,
			"bgName": "bg_hms_7"
		},
		{
			"actor": 205090,
			"side": 2,
			"dir": 1,
			"nameColor": "#a9f548",
			"expression": 2,
			"say": "\u82f1\u52c7\uff0c\u8fd9\u6279\u585e\u58ec\u7684\u6570\u91cf\u548c\u8d28\u91cf\u4e0d\u662f\u62a4\u822a\u8230\u961f\u80fd\u5e94\u4ed8\u7684\u3002",
			"typewriter": {
				"speed": 0.05,
				"speedUp": 0.01
			},
			"painting": {
				"alpha": 0.3,
				"time": 1
			},
			"bgName": "bg_hms_7"
		},
		{
			"say": "\u5982\u679c\u6211\u4eec\u4e0d\u5f7b\u5e95\u89e3\u51b3\u7684\u8bdd\uff0c\u4e4b\u540e\u7684\u62a4\u822a\u8239\u56e2\u5c31\u5371\u9669\u4e86\u3002",
			"actor": 205090,
			"side": 2,
			"dir": 1,
			"nameColor": "#a9f548",
			"typewriter": {
				"speed": 0.05,
				"speedUp": 0.01
			},
			"painting": {
				"alpha": 0.3,
				"time": 1
			},
			"bgName": "bg_hms_7"
		},
		{
			"actor": 201330,
			"side": 2,
			"dir": 1,
			"nameColor": "#a9f548",
			"expression": 2,
			"say": "\u53ef\u662f\u652f\u63f4\u8230\u961f\u8fd8\u5728\u8fdb\u884c\u8bf1\u5bfc\u4f5c\u6218\uff0c\u5982\u679c\u6211\u4eec\u4e0d\u5feb\u70b9\u8d76\u8fc7\u53bb\u7684\u8bdd\u2026\u2026\u5979\u4eec\u5c31\u5371\u9669\u4e86\uff01",
			"typewriter": {
				"speed": 0.05,
				"speedUp": 0.01
			},
			"painting": {
				"alpha": 0.3,
				"time": 1
			},
			"bgName": "bg_hms_7"
		},
		{
			"say": "\u545c....\u4e0d\u80fd\u770b\u7740\u62a4\u822a\u8230\u961f\u649e\u4e0a\u585e\u58ec\uff0c\u4e5f\u4e0d\u80fd\u653e\u7740\u652f\u63f4\u8230\u961f\u4e0d\u7ba1\u2026",
			"actor": 202110,
			"side": 2,
			"dir": 1,
			"nameColor": "#a9f548",
			"typewriter": {
				"speed": 0.05,
				"speedUp": 0.01
			},
			"painting": {
				"alpha": 0.3,
				"time": 1
			},
			"bgName": "bg_hms_7"
		},
		{
			"actor": 205100,
			"side": 2,
			"dir": 1,
			"nameColor": "#a9f548",
			"expression": 2,
			"say": "\u7acb\u523b\u8054\u7cfb\u53f8\u4ee4\u90e8\u62a5\u544a\u73b0\u5728\u7684\u60c5\u51b5\uff01\u5982\u679c\u653e\u5f03\u6b7c\u706d\u94c1\u8840\u4e3b\u529b\u8230\u961f\u7684\u4f5c\u6218\uff0c\u652f\u63f4\u8230\u961f\u8fd8\u6709\u5411\u672c\u571f\u65b9\u5411\u64a4\u9000\u7684\u9009\u9879\u3002",
			"typewriter": {
				"speed": 0.05,
				"speedUp": 0.01
			},
			"painting": {
				"alpha": 0.3,
				"time": 1
			},
			"bgName": "bg_hms_7"
		},
		{
			"say": "\u8fd9\u6837\u7684\u8bdd\u5c31\u4f1a\u6362\u6210\u6211\u4eec\u88ab\u94c1\u8840\u8230\u961f\u548c\u585e\u58ec\u8230\u961f\u5939\u51fb\u4e86\u54e6\uff1f",
			"actor": 205090,
			"side": 2,
			"dir": 1,
			"nameColor": "#a9f548",
			"typewriter": {
				"speed": 0.05,
				"speedUp": 0.01
			},
			"painting": {
				"alpha": 0.3,
				"time": 1
			},
			"bgName": "bg_hms_7"
		},
		{
			"actor": 205100,
			"side": 2,
			"dir": 1,
			"nameColor": "#a9f548",
			"expression": 2,
			"say": "\u5230\u90a3\u65f6\u5019\uff0c\u5c31\u7531\u6211\u4eec\u5c31\u628a\u5b83\u4eec\u5168\u90e8\u90fd\u89e3\u51b3\u6389\uff01",
			"typewriter": {
				"speed": 0.05,
				"speedUp": 0.01
			},
			"painting": {
				"alpha": 0.3,
				"time": 1
			},
			"bgName": "bg_hms_7"
		},
		{
			"say": "\u2014\u2014\u2014\u2014\u2014\u2014\u2014\u2014",
			"typewriter": {
				"speed": 0.05,
				"speedUp": 0.01
			},
			"side": 2,
			"dir": 1,
			"nameColor": "#a9f548",
			"actorName": "\u901a\u8baf\u5668",
			"painting": {
				"alpha": 0.3,
				"time": 1
			},
			"bgName": "bg_hms_7"
		},
		{
			"actor": 202110,
			"side": 2,
			"dir": 1,
			"nameColor": "#a9f548",
			"say": "\u4e0d\u3001\u4e0d\u884c..\u901a\u8baf\u5668\u6ca1\u6709\u53cd\u5e94\uff01",
			"typewriter": {
				"speed": 0.05,
				"speedUp": 0.01
			},
			"action": [
				{
					"y": 45,
					"type": "shake",
					"dur": 0.15,
					"number": 2,
					"delay": 0,
					"x": 0
				}
			],
			"painting": {
				"alpha": 0.3,
				"time": 1
			},
			"bgName": "bg_hms_7"
		},
		{
			"actor": 205100,
			"side": 2,
			"dir": 1,
			"nameColor": "#a9f548",
			"expression": 2,
			"say": "\u901a\u8baf\u5668\u600e\u4e48\u8001\u662f\u5728\u5173\u952e\u65f6\u5019\u5931\u7075\u554a\uff01\u662f\u521a\u624d\u7684\u585e\u58ec\u5e72\u7684\u597d\u4e8b\u4e48...\u6c14\u6b7b\u6211\u4e86\uff01",
			"typewriter": {
				"speed": 0.05,
				"speedUp": 0.01
			},
			"painting": {
				"alpha": 0.3,
				"time": 1
			},
			"bgName": "bg_hms_7"
		},
		{
			"actor": 201330,
			"side": 2,
			"dir": 1,
			"nameColor": "#a9f548",
			"expression": 2,
			"say": "\u545c\u2026\u548c\u5927\u5bb6\u8054\u7cfb\u4e0d\u4e0a\u5c31\u4e0d\u80fd\u8ba9\u5979\u4eec\u64a4\u9000\u4e86\uff0c\u63a5\u4e0b\u6765\u5e94\u8be5\u600e\u4e48\u529e\u554a\u2026",
			"typewriter": {
				"speed": 0.05,
				"speedUp": 0.01
			},
			"painting": {
				"alpha": 0.3,
				"time": 1
			},
			"bgName": "bg_hms_7"
		},
		{
			"say": "\u2026\u65f6\u95f4\u7d27\u8feb\uff0c\u82f1\u52c7\uff0c\u4f60\u548c\u6211\u662f\u8fd9\u6b21\u884c\u52a8\u7684\u8d1f\u8d23\u4eba\uff0c\u4e00\u8d77\u6765\u4e0b\u4e2a\u51b3\u65ad\u5427\u3002",
			"actor": 205090,
			"side": 2,
			"dir": 1,
			"nameColor": "#a9f548",
			"typewriter": {
				"speed": 0.05,
				"speedUp": 0.01
			},
			"painting": {
				"alpha": 0.3,
				"time": 1
			},
			"bgName": "bg_hms_7"
		},
		{
			"actor": 205100,
			"side": 2,
			"dir": 1,
			"nameColor": "#a9f548",
			"expression": 3,
			"say": "\u2026\u547c...\u518d\u5206\u6790\u4e00\u4e0b\u73b0\u72b6\u5427\u3002",
			"typewriter": {
				"speed": 0.05,
				"speedUp": 0.01
			},
			"painting": {
				"alpha": 0.3,
				"time": 1
			},
			"bgName": "bg_hms_7"
		},
		{
			"actor": 205100,
			"side": 2,
			"dir": 1,
			"nameColor": "#a9f548",
			"expression": 1,
			"say": "\u539f\u672c\uff0c\u8fd9\u6b21\u7684\u4efb\u52a1\u5c31\u662f\u652f\u63f4\u5317\u65b9\u8054\u5408\u7684\u8239\u56e2\u62a4\u822a\u4efb\u52a1\uff0c\u5bf9\u94c1\u8840\u8230\u961f\u7684\u4f5c\u6218\u53ea\u662f\u9644\u52a0\u9009\u9879\u2026",
			"typewriter": {
				"speed": 0.05,
				"speedUp": 0.01
			},
			"painting": {
				"alpha": 0.3,
				"time": 1
			},
			"bgName": "bg_hms_7"
		},
		{
			"actor": 205100,
			"side": 2,
			"dir": 1,
			"nameColor": "#a9f548",
			"expression": 3,
			"say": "\u5982\u679c\u6211\u4eec\u6389\u5934\u79bb\u5f00\uff0c\u8239\u56e2\u5c31\u4f1a\u906d\u9047\u5230\u585e\u58ec\u7684\u76f4\u63a5\u653b\u51fb\uff0c\u7136\u540e\u2026",
			"typewriter": {
				"speed": 0.05,
				"speedUp": 0.01
			},
			"painting": {
				"alpha": 0.3,
				"time": 1
			},
			"bgName": "bg_hms_7"
		},
		{
			"actor": 205090,
			"side": 2,
			"dir": 1,
			"nameColor": "#a9f548",
			"expression": 3,
			"say": "\u55ef\uff0c\u6050\u6015\u4e00\u8258\u90fd\u4e0d\u4f1a\u5e78\u5b58\u4e0b\u6765\u3002\u6781\u5730\u585e\u58ec\u7684\u5b9e\u529b\uff0c\u521a\u521a\u6211\u4eec\u5df2\u7ecf\u4eb2\u8eab\u4f53\u4f1a\u8fc7\u4e86\u3002",
			"typewriter": {
				"speed": 0.05,
				"speedUp": 0.01
			},
			"painting": {
				"alpha": 0.3,
				"time": 1
			},
			"bgName": "bg_hms_7"
		},
		{
			"actor": 205100,
			"side": 2,
			"dir": 1,
			"nameColor": "#a9f548",
			"expression": 3,
			"say": "\u5982\u679c\u652f\u63f4\u7269\u8d44\u4e0d\u80fd\u5230\u8fbe\u5317\u65b9\u8054\u5408\uff0c\u6781\u5730\u9632\u7ebf\u6050\u6015\u5f88\u5feb\u5c31\u4f1a\u5d29\u6e83\u74e6\u89e3\u5427......",
			"typewriter": {
				"speed": 0.05,
				"speedUp": 0.01
			},
			"painting": {
				"alpha": 0.3,
				"time": 1
			},
			"bgName": "bg_hms_7"
		},
		{
			"actor": 205090,
			"side": 2,
			"dir": 1,
			"nameColor": "#a9f548",
			"expression": 2,
			"say": "\u5230\u90a3\u65f6\uff0c\u6781\u5730\u548cNY\u6d77\u57df\u7684\u585e\u58ec\u4f1a\u8fde\u6210\u4e00\u7247\uff0c\u5c06\u7687\u5bb6\u5c06\u53d8\u6210\u5927\u6d0b\u4e0a\u7684\u5b64\u5c9b\u3002",
			"typewriter": {
				"speed": 0.05,
				"speedUp": 0.01
			},
			"painting": {
				"alpha": 0.3,
				"time": 1
			},
			"bgName": "bg_hms_7"
		},
		{
			"actor": 205100,
			"side": 2,
			"dir": 1,
			"nameColor": "#a9f548",
			"expression": 3,
			"say": "\u6240\u4ee5\u8bf4......\u6211\u4eec\u73b0\u5728\u6389\u5934\u7684\u8bdd\uff0c\u662f\u5bf9\u8239\u56e2\u548c\u5317\u65b9\u8054\u5408\u7684\u4e0d\u8d1f\u8d23\u4efb\uff0c\u4e5f\u662f\u5bf9\u4e8e\u6574\u4e2a\u6218\u5c40\u7684\u4e0d\u8d1f\u8d23\u4efb\u2026",
			"typewriter": {
				"speed": 0.05,
				"speedUp": 0.01
			},
			"painting": {
				"alpha": 0.3,
				"time": 1
			},
			"bgName": "bg_hms_7"
		},
		{
			"say": "\u6211\u4eec\u6b63\u5728\u5bf9\u6297\u5171\u540c\u7684\u654c\u4eba\uff0c\u800c\u4e14\u6211\u4eec\u9700\u8981\u76f8\u4e92\u5e2e\u52a9\u624d\u80fd\u53d6\u5f97\u6700\u7ec8\u7684\u80dc\u5229\u3002",
			"actor": 205090,
			"side": 2,
			"dir": 1,
			"nameColor": "#a9f548",
			"typewriter": {
				"speed": 0.05,
				"speedUp": 0.01
			},
			"painting": {
				"alpha": 0.3,
				"time": 1
			},
			"bgName": "bg_hms_7"
		},
		{
			"actor": 205100,
			"side": 2,
			"dir": 1,
			"nameColor": "#a9f548",
			"expression": 3,
			"say": "\u55ef.........\u6211\u51b3\u5b9a\u4e86\uff0c\u4e3b\u529b\u8230\u961f\u4e0d\u8fd4\u822a\u3002",
			"typewriter": {
				"speed": 0.05,
				"speedUp": 0.01
			},
			"painting": {
				"alpha": 0.3,
				"time": 1
			},
			"bgName": "bg_hms_7"
		},
		{
			"actor": 205100,
			"side": 2,
			"dir": 1,
			"nameColor": "#a9f548",
			"expression": 2,
			"say": "\u6211\u4eec\u7559\u5728\u8fd9\u91cc\u7ee7\u7eed\u6218\u6597\u3002\u5982\u679c\u585e\u58ec\u9760\u8fd1\u5c31\u6d88\u706d\u585e\u58ec\uff0c\u5982\u679c\u94c1\u8840\u9760\u8fd1\u5c31\u89e3\u51b3\u94c1\u8840\u3002\u6d88\u706d\u4e00\u5207\u654c\u4eba......\u4e0d\u60dc\u4ee3\u4ef7\u4fdd\u62a4\u6781\u5730\u8239\u56e2\u7684\u5b89\u5168\uff01",
			"typewriter": {
				"speed": 0.05,
				"speedUp": 0.01
			},
			"effects": [
				{
					"name": "speed",
					"active": true
				}
			],
			"painting": {
				"alpha": 0.3,
				"time": 1
			},
			"bgName": "bg_hms_7"
		},
		{
			"actor": 201330,
			"side": 2,
			"dir": 1,
			"nameColor": "#a9f548",
			"expression": 2,
			"say": "\u90a3\u2026\u652f\u63f4\u8230\u961f\u90a3\u8fb9\u600e\u4e48\u529e\uff1f",
			"typewriter": {
				"speed": 0.05,
				"speedUp": 0.01
			},
			"effects": [
				{
					"name": "speed",
					"active": false
				}
			],
			"painting": {
				"alpha": 0.3,
				"time": 1
			},
			"bgName": "bg_hms_7"
		},
		{
			"actor": 205100,
			"side": 2,
			"dir": 1,
			"nameColor": "#a9f548",
			"expression": 3,
			"say": "\u2026\u7ee7\u7eed\u68c0\u67e5\u901a\u8baf\u8bbe\u5907\uff0c\u4e00\u65e6\u901a\u8baf\u6062\u590d\uff0c\u7acb\u523b\u8ba9\u5979\u4eec\u5411\u672c\u571f\u65b9\u5411\u64a4\u9000\uff01",
			"typewriter": {
				"speed": 0.05,
				"speedUp": 0.01
			},
			"painting": {
				"alpha": 0.3,
				"time": 1
			},
			"bgName": "bg_hms_7"
		},
		{
			"say": "\u5514\u2026\u8fd9\u4e0b\u8981\u8fdd\u80cc\u965b\u4e0b\u7684\u547d\u4ee4\u4e86\u5462\u3002",
			"actor": 202110,
			"side": 2,
			"dir": 1,
			"nameColor": "#a9f548",
			"typewriter": {
				"speed": 0.05,
				"speedUp": 0.01
			},
			"painting": {
				"alpha": 0.3,
				"time": 1
			},
			"bgName": "bg_hms_7"
		},
		{
			"say": "\u65f6\u5c40\u96be\u6d4b\uff0c\u65e2\u7136\u5df2\u7ecf\u662f\u8fd9\u79cd\u72b6\u51b5\u4e86\uff0c\u51b3\u5b9a\u4e86\u5c31\u884c\u52a8\u8d77\u6765\uff01\u56de\u5934\u518d\u601d\u8003\u600e\u4e48\u8ddf\u965b\u4e0b\u6c47\u62a5\u5427\uff01",
			"actor": 205090,
			"side": 2,
			"dir": 1,
			"nameColor": "#a9f548",
			"typewriter": {
				"speed": 0.05,
				"speedUp": 0.01
			},
			"painting": {
				"alpha": 0.3,
				"time": 1
			},
			"bgName": "bg_hms_7"
		},
		{
			"actor": 205100,
			"side": 2,
			"dir": 1,
			"nameColor": "#a9f548",
			"blackBg": true,
			"say": "\u8d23\u4efb\u4ec0\u4e48\u7684\uff0c\u6211\u6765\u62c5\u7740\u5c31\u662f\u4e86\uff01\u585e\u58ec\u8230\u961f\u53c8\u9760\u8fc7\u6765\u4e86\uff0c\u8981\u62fc\u52b2\u5168\u529b\u8fce\u6218\u4e86\u54e6\uff01",
			"typewriter": {
				"speed": 0.05,
				"speedUp": 0.01
			},
			"painting": {
				"alpha": 0.3,
				"time": 1
			},
			"bgName": "bg_hms_7"
		}
	],
	"id": "YONGYEHUANGUANG19",
	"mode": 2,
	"fadeType": 2,
	"once": true
}