{
	"id": "AKASHI8",
	"mode": 2,
	"once": true,
	"scripts": [
		{
			"actor": 312010,
			"side": 2,
			"dir": -1,
			"typewriter": {
				"speed": 0.05,
				"speedUp": 0.01
			},
			"painting": {
				"alpha": 0.3,
				"time": 1
			},
			"say": "\u679c\u7136{namecode:98}\u662f\u7d55\u5c0d\u4e0d\u6703\u51fa\u932f\u7684\u55b5\uff01\u611f\u8b1d\u6307\u63ee\u5b98\u7684\u914d\u5408\u55b5\uff01\u9019\u4e0b{namecode:20}\u4e5f\u7121\u8a71\u53ef\u8aaa\u4e86\u55b5\uff01"
		},
		{
			"actor": 312010,
			"side": 2,
			"dir": -1,
			"typewriter": {
				"speed": 0.05,
				"speedUp": 0.01
			},
			"painting": {
				"alpha": 0.3,
				"time": 1
			},
			"say": "\u2014\u2014\u55b5\uff1f\u6307\u63ee\u5b98\u4eca\u5929\u4e5f\u8981\u5e36\u8457\u8266\u968a\u51fa\u64ca\u55b5\uff1f"
		},
		{
			"actor": 312010,
			"side": 2,
			"dir": -1,
			"typewriter": {
				"speed": 0.05,
				"speedUp": 0.01
			},
			"painting": {
				"alpha": 0.3,
				"time": 1
			},
			"say": "\u6307\u63ee\u5b98\u771f\u52e4\u52de\u55b5\uff5e\u52a0\u6cb9\u55b5\uff5e"
		}
	]
}